model/__init__.py
model/dataset.py
model/loss.py
model/metrics.py
model/model.py
model/performer_attention.py
model/scRNAlayer.py
model/scTCRlayer.py
model/utils.py
mist_vae-1.0.0.dist-info/LICENSE
mist_vae-1.0.0.dist-info/METADATA
mist_vae-1.0.0.dist-info/WHEEL
mist_vae-1.0.0.dist-info/entry_points.txt
mist_vae-1.0.0.dist-info/top_level.txt
mist_vae-1.0.0.dist-info/RECORD
