Metadata-Version: 2.1
Name: mist-vae
Version: 1.0.0
Summary: MIST: an interpretable and flexible deep learning framework for single-T cell transcriptome and receptor analysis
Author: Lai Wenpu
Author-email: Lai Wenpu <kyzy850520@163.com>
License: GNU GENERAL PUBLIC LICENSE
Project-URL: Homepage, https://github.com/aapupu/MIST
Classifier: Development Status :: 3 - Alpha
Classifier: Programming Language :: Python :: 3
Classifier: License :: OSI Approved :: GNU General Public License v3 (GPLv3)
Classifier: Operating System :: OS Independent
Classifier: Topic :: Scientific/Engineering :: Bio-Informatics
Classifier: Intended Audience :: Science/Research
Classifier: Operating System :: Microsoft :: Windows
Classifier: Operating System :: POSIX :: Linux
Requires-Python: >=3.7
License-File: LICENSE
Requires-Dist: numpy >=1.21.6
Requires-Dist: pandas >=1.3.5
Requires-Dist: anndata >=0.8.0
Requires-Dist: scipy >=1.7.3
Requires-Dist: scikit-learn >=1.0.2
Requires-Dist: scanpy >=1.9.3
Requires-Dist: scirpy >=0.12.0
Requires-Dist: torch >=1.13.0
Requires-Dist: einops >=0.6.0
Requires-Dist: tqdm >=4.64.1
Requires-Dist: prefetch-generator >=1.0.3
Requires-Dist: local-attention >=1.5.7
Requires-Dist: leidenalg >=0.10.2
